{
	"name": "Group_CHG",
	"properties": {
		"linkedServiceName": {
			"referenceName": "AzurePostgreSql1master",
			"type": "LinkedServiceReference"
		},
		"annotations": [],
		"type": "AzurePostgreSqlTable",
		"schema": [
			{
				"name": "id",
				"type": "integer",
				"precision": 0,
				"scale": 0
			},
			{
				"name": "object_type",
				"type": "character",
				"precision": 0,
				"scale": 0
			},
			{
				"name": "group_type",
				"type": "character",
				"precision": 0,
				"scale": 0
			},
			{
				"name": "argument",
				"type": "character varying",
				"precision": 0,
				"scale": 0
			},
			{
				"name": "function_enum",
				"type": "character",
				"precision": 0,
				"scale": 0
			},
			{
				"name": "organization_id",
				"type": "integer",
				"precision": 0,
				"scale": 0
			},
			{
				"name": "ref_id",
				"type": "integer",
				"precision": 0,
				"scale": 0
			},
			{
				"name": "name",
				"type": "character varying",
				"precision": 0,
				"scale": 0
			},
			{
				"name": "description",
				"type": "character varying",
				"precision": 0,
				"scale": 0
			},
			{
				"name": "created_at",
				"type": "bigint",
				"precision": 0,
				"scale": 0
			},
			{
				"name": "chg_flg",
				"type": "character varying",
				"precision": 0,
				"scale": 0
			},
			{
				"name": "load_dt",
				"type": "timestamp without time zone",
				"precision": 0,
				"scale": 0
			}
		],
		"typeProperties": {
			"schema": "staging",
			"table": "group_chg"
		}
	}
}